dakara_base/__init__.py
dakara_base/config.py
dakara_base/directory.py
dakara_base/exceptions.py
dakara_base/http_client.py
dakara_base/progress_bar.py
dakara_base/safe_workers.py
dakara_base/utils.py
dakara_base/version.py
dakara_base/version_check.py
dakara_base/websocket_client.py
dakarabase-2.1.0.dist-info/LICENSE
dakarabase-2.1.0.dist-info/METADATA
dakarabase-2.1.0.dist-info/WHEEL
dakarabase-2.1.0.dist-info/top_level.txt
dakarabase-2.1.0.dist-info/RECORD
