Metadata-Version: 2.2
Name: dakarabase
Version: 2.1.0
Summary: Collection of helper modules for the Dakara Project
Author-email: Neraste <neraste.herr10@gmail.com>
License: MIT License
Project-URL: Homepage, https://github.com/DakaraProject/dakara-base
Project-URL: Repository, https://github.com/DakaraProject/dakara-base.git
Project-URL: Issues, https://github.com/DakaraProject/dakara-base/issues
Project-URL: Changelog, https://github.com/DakaraProject/dakara-base/blob/master/CHANGELOG.md
Classifier: License :: OSI Approved :: MIT License
Classifier: Programming Language :: Python
Classifier: Programming Language :: Python :: 3
Classifier: Programming Language :: Python :: 3.9
Classifier: Programming Language :: Python :: 3.10
Classifier: Programming Language :: Python :: 3.11
Classifier: Programming Language :: Python :: 3.12
Classifier: Programming Language :: Python :: 3.13
Classifier: Operating System :: OS Independent
Classifier: Environment :: Console
Classifier: Intended Audience :: Developers
Requires-Python: >=3.9
License-File: LICENSE
Requires-Dist: coloredlogs<15.1.0,>=15.0.1
Requires-Dist: environs<14.2.0,>=14.1.1
Requires-Dist: furl<2.2.0,>=2.1.3
Requires-Dist: platformdirs<4.4.0,>=4.3.6
Requires-Dist: progressbar2<4.6.0,>=4.5.0
Requires-Dist: PyYAML<6.1,>=6.0.2
Requires-Dist: requests<2.33.0,>=2.32.3
Requires-Dist: websocket-client<1.9.0,>=1.8.0
Provides-Extra: dev
Requires-Dist: black<25.2.0,>=25.1.0; extra == "dev"
Requires-Dist: codecov<2.2.0,>=2.1.13; extra == "dev"
Requires-Dist: isort<6.1.0,>=6.0.0; extra == "dev"
Requires-Dist: pdoc<15.2.0,>=15.0.1; extra == "dev"
Requires-Dist: pre-commit<4.2.0,>=4.1.0; extra == "dev"
Requires-Dist: pytest-cov<6.1.0,>=6.0.0; extra == "dev"
Requires-Dist: pytest<8.4.0,>=8.3.4; extra == "dev"
Requires-Dist: ruff<0.10.0,>=0.9.6; extra == "dev"
